devopness/__init__.py
devopness/base/__init__.py
devopness/base/base_model.py
devopness/base/base_service.py
devopness/client.py
devopness/client_config.py
devopness/core/__init__.py
devopness/core/api_error.py
devopness/core/network_error.py
devopness/core/response.py
devopness/core/sdk_error.py
devopness/generated/__init__.py
devopness/generated/api/__init__.py
devopness/generated/api/actions_api.py
devopness/generated/api/actions_logs_api.py
devopness/generated/api/applications_api.py
devopness/generated/api/applications_hooks_api.py
devopness/generated/api/applications_variables_api.py
devopness/generated/api/credentials_api.py
devopness/generated/api/credentials_repositories_api.py
devopness/generated/api/cron_jobs_api.py
devopness/generated/api/daemons_api.py
devopness/generated/api/environments_actions_api.py
devopness/generated/api/environments_api.py
devopness/generated/api/environments_team_memberships_api.py
devopness/generated/api/environments_teams_api.py
devopness/generated/api/hook_requests_api.py
devopness/generated/api/hooks_api.py
devopness/generated/api/hooks_requests_api.py
devopness/generated/api/network_rules_api.py
devopness/generated/api/networks_api.py
devopness/generated/api/networks_subnets_api.py
devopness/generated/api/organizations_api.py
devopness/generated/api/pipelines_actions_api.py
devopness/generated/api/pipelines_api.py
devopness/generated/api/pipelines_hooks_api.py
devopness/generated/api/pipelines_steps_api.py
devopness/generated/api/projects_actions_api.py
devopness/generated/api/projects_api.py
devopness/generated/api/projects_api_tokens_api.py
devopness/generated/api/projects_archived_environments_api.py
devopness/generated/api/projects_environments_api.py
devopness/generated/api/projects_roles_api.py
devopness/generated/api/projects_teams_api.py
devopness/generated/api/resource_events_api.py
devopness/generated/api/resource_links_api.py
devopness/generated/api/roles_api.py
devopness/generated/api/servers_api.py
devopness-2.1.10.dist-info/METADATA
devopness-2.1.10.dist-info/WHEEL
devopness-2.1.10.dist-info/RECORD
