Metadata-Version: 2.4
Name: devopness
Version: 2.1.10
Summary: Devopness API Python SDK - Painless essential DevOps to everyone
License-Expression: MIT
Keywords: API Client,Cloud Engineering,Cloud Infrastructure,Cloud Platform,Cloud Resource Management,Configuration Management,Deployment Automation,Devopness,DevOps,Infrastructure as Code,Platform Engineering,Python SDK,Server Management,Server Provisioning,Zero Downtime Deployment
Author: Devopness (https://www.devopness.com)
Requires-Python: >=3.11
Classifier: Development Status :: 5 - Production/Stable
Classifier: Environment :: Console
Classifier: Framework :: Pydantic
Classifier: Intended Audience :: Developers
Classifier: Intended Audience :: System Administrators
Classifier: License :: OSI Approved :: MIT License
Classifier: Operating System :: OS Independent
Classifier: Programming Language :: Python
Classifier: Programming Language :: Python :: 3
Classifier: Programming Language :: Python :: 3.11
Classifier: Programming Language :: Python :: 3.12
Classifier: Programming Language :: Python :: 3.13
Classifier: Topic :: Software Development
Classifier: Topic :: Software Development :: Libraries
Classifier: Topic :: Software Development :: Libraries :: Python Modules
Classifier: Topic :: System :: Systems Administration
Classifier: Topic :: Utilities
Requires-Dist: httpcore (>=1.0.9)
Requires-Dist: httpx (>=0.28.1,<0.29.0)
Requires-Dist: pydantic (>=2.11.3,<3.0.0)
Project-URL: Homepage, https://www.devopness.com
Project-URL: Repository, https://github.com/devopness/devopness
